{
  "VK_Q": ";",
  "VK_W": "ς",
  "VK_E": "ε",
  "VK_R": "ρ",
  "VK_T": "τ",
  "VK_Y": "υ",
  "VK_U": "θ",
  "VK_I": "ι",
  "VK_O": "ο",
  "VK_P": "π",
  "OEM_4": "[",
  "OEM_6": "]",
  "OEM_5": "\\",
  "VK_A": "α",
  "VK_S": "σ",
  "VK_D": "δ",
  "VK_F": "φ",
  "VK_G": "γ",
  "VK_H": "η",
  "VK_J": "ξ",
  "VK_K": "κ",
  "VK_L": "λ",
  "OEM_1": "΄",
  "OEM_7": "'",
  "VK_Z": "ζ",
  "VK_X": "χ",
  "VK_C": "ψ",
  "VK_V": "ω",
  "VK_B": "β",
  "VK_N": "ν",
  "VK_M": "μ",
  "OEM_COMMA": ",",
  "OEM_PERIOD": ".",
  "OEM_2": "/"
}